oks_cli/__init__.py
oks_cli/cache.py
oks_cli/cluster.py
oks_cli/main.py
oks_cli/profile.py
oks_cli/project.py
oks_cli/quotas.py
oks_cli/utils.py
oks_cli-1.16.dist-info/licenses/LICENSE
oks_cli-1.16.dist-info/METADATA
oks_cli-1.16.dist-info/WHEEL
oks_cli-1.16.dist-info/entry_points.txt
oks_cli-1.16.dist-info/top_level.txt
oks_cli-1.16.dist-info/RECORD
