Metadata-Version: 2.4
Name: oks-cli
Version: 1.16
Author: Outscale SAS
Author-email: opensource@outscale.com
License: BSD
Classifier: License :: OSI Approved :: BSD License
Classifier: Programming Language :: Python :: 3
Classifier: Programming Language :: Python :: 3.6
Classifier: Programming Language :: Python :: 3.7
Classifier: Programming Language :: Python :: 3.8
Classifier: Programming Language :: Python :: 3.9
Classifier: Programming Language :: Python :: 3.10
Classifier: Programming Language :: Python :: 3.11
Classifier: Operating System :: OS Independent
License-File: LICENSE
Requires-Dist: certifi>=2024.8.30
Requires-Dist: charset-normalizer>=3.3.2
Requires-Dist: click<8.3.0,>=8.1.7
Requires-Dist: colorama>=0.4.6
Requires-Dist: idna>=3.10
Requires-Dist: pyyaml>=6.0.2
Requires-Dist: requests>=2.32.3
Requires-Dist: urllib3>=2.2.3
Requires-Dist: human-readable
Requires-Dist: prettytable
Requires-Dist: python-dateutil
Requires-Dist: altgraph>=0.17.4
Requires-Dist: pynacl>=1.5.0
Requires-Dist: pyOpenSSL>=25.0.0
Provides-Extra: dev
Requires-Dist: pytest>=8.4.1; extra == "dev"
Dynamic: author
Dynamic: author-email
Dynamic: classifier
Dynamic: description
Dynamic: description-content-type
Dynamic: license
Dynamic: license-file
Dynamic: provides-extra
Dynamic: requires-dist
